MANIFEST.in
README.md
setup.py
sim_adjuster/__init__.py
sim_adjuster/__main__.py
sim_adjuster/ferment_sim.py
sim_adjuster/mash_sim.py
sim_adjuster.egg-info/PKG-INFO
sim_adjuster.egg-info/SOURCES.txt
sim_adjuster.egg-info/dependency_links.txt
sim_adjuster.egg-info/requires.txt
sim_adjuster.egg-info/top_level.txt
test/test_ferment_sim.py
test/test_mash_sim.py