Metadata-Version: 2.1
Name: sim-adjuster
Version: 0.1
Summary: UNKNOWN
Home-page: https://github.com/BrewBlox/sim-adjuster
Author: BrewPi
Author-email: development@brewpi.com
License: UNKNOWN
Keywords: brewing brewpi brewblox development
Platform: UNKNOWN
Classifier: Development Status :: 4 - Beta
Classifier: License :: OSI Approved :: GNU General Public License (GPL)
Classifier: Programming Language :: Python :: 3.7
Classifier: Topic :: System :: Hardware
Requires-Python: >=3.7
Provides-Extra: dev
